pymol_labimm/__init__.py
pymol_labimm/capabilities.py
pymol_labimm/commons.py
pymol_labimm/prefs.py
pymol_labimm/vina.py
pymol_labimm/docking/__init__.py
pymol_labimm/docking/old_vina.py
pymol_labimm/docking/vina.py
pymol_labimm/fetch_similar/__init__.py
pymol_labimm/fetch_similar/blast.py
pymol_labimm/fetch_similar/blast_gui.py
pymol_labimm/fetch_similar/shape3d.py
pymol_labimm/fetch_similar/shape3d_gui.py
pymol_labimm/ftmap/__init__.py
pymol_labimm/ftmap/core.py
pymol_labimm/ftmap/gui.py
pymol_labimm/tests/__init__.py
pymol_labimm/tests/conftest.py
pymol_labimm/tests/test_ftmap.py
pymol_labimm/tests/test_vina.py
pymol_labimm/tests/data/__init__.py
pymol_labimm-0.13.6.dist-info/METADATA
pymol_labimm-0.13.6.dist-info/WHEEL
pymol_labimm-0.13.6.dist-info/top_level.txt
pymol_labimm-0.13.6.dist-info/RECORD
